[{"speciesCode":"wfwduc1","comName":"White-faced Whistling-Duck"},{"speciesCode":"bbwduc","comName":"Black-bellied Whistling-Duck"},{"speciesCode":"wiwduc1","comName":"West Indian Whistling-Duck"},{"speciesCode":"fuwduc","comName":"Fulvous Whistling-Duck"},{"speciesCode":"empgoo","comName":"Emperor Goose"},{"speciesCode":"snogoo","comName":"Snow Goose"},{"speciesCode":"rosgoo","comName":"Ross's Goose"},{"speciesCode":"gragoo","comName":"Graylag Goose"},{"speciesCode":"gwfgoo","comName":"Greater White-fronted Goose"},{"speciesCode":"lwfgoo","comName":"Lesser White-fronted Goose"},{"speciesCode":"taibeg1","comName":"Taiga Bean-Goose"},{"speciesCode":"tunbeg1","comName":"Tundra Bean-Goose"},{"speciesCode":"pifgoo","comName":"Pink-footed Goose"},{"speciesCode":"brant","comName":"Brant"},{"speciesCode":"bargoo","comName":"Barnacle Goose"},{"speciesCode":"cacgoo1","comName":"Cackling Goose"},{"speciesCode":"cangoo","comName":"Canada Goose"},{"speciesCode":"hawgoo","comName":"Hawaiian Goose"},{"speciesCode":"mutswa","comName":"Mute Swan"},{"speciesCode":"blkswa","comName":"Black Swan"},{"speciesCode":"truswa","comName":"Trumpeter Swan"},{"speciesCode":"tunswa","comName":"Tundra Swan"},{"speciesCode":"whoswa","comName":"Whooper Swan"},{"speciesCode":"egygoo","comName":"Egyptian Goose"},{"speciesCode":"rudshe","comName":"Ruddy Shelduck"},{"speciesCode":"comshe","comName":"Common Shelduck"},{"speciesCode":"musduc","comName":"Muscovy Duck"},{"speciesCode":"rintea1","comName":"Ringed Teal"},{"speciesCode":"wooduc","comName":"Wood Duck"},{"speciesCode":"manduc","comName":"Mandarin Duck"},{"speciesCode":"baitea","comName":"Baikal Teal"},{"speciesCode":"gargan","comName":"Garganey"},{"speciesCode":"buwtea","comName":"Blue-winged Teal"},{"speciesCode":"cintea","comName":"Cinnamon Teal"},{"speciesCode":"norsho","comName":"Northern Shoveler"},{"speciesCode":"gadwal","comName":"Gadwall"},{"speciesCode":"falduc","comName":"Falcated Duck"},{"speciesCode":"eurwig","comName":"Eurasian Wigeon"},{"speciesCode":"amewig","comName":"American Wigeon"},{"speciesCode":"layduc","comName":"Laysan Duck"},{"speciesCode":"hawduc","comName":"Hawaiian Duck"},{"speciesCode":"spbduc","comName":"Eastern Spot-billed Duck"},{"speciesCode":"mallar3","comName":"Mallard"},{"speciesCode":"mexduc","comName":"Mexican Duck"},{"speciesCode":"ambduc","comName":"American Black Duck"},{"speciesCode":"motduc","comName":"Mottled Duck"},{"speciesCode":"whcpin","comName":"White-cheeked Pintail"},{"speciesCode":"norpin","comName":"Northern Pintail"},{"speciesCode":"gnwtea","comName":"Green-winged Teal"},{"speciesCode":"recpoc","comName":"Red-crested Pochard"},{"speciesCode":"robpoc1","comName":"Rosy-billed Pochard"},{"speciesCode":"canvas","comName":"Canvasback"},{"speciesCode":"redhea","comName":"Redhead"},{"speciesCode":"compoc","comName":"Common Pochard"},{"speciesCode":"rinduc","comName":"Ring-necked Duck"},{"speciesCode":"tufduc","comName":"Tufted Duck"},{"speciesCode":"gresca","comName":"Greater Scaup"},{"speciesCode":"lessca","comName":"Lesser Scaup"},{"speciesCode":"steeid","comName":"Steller's Eider"},{"speciesCode":"speeid","comName":"Spectacled Eider"},{"speciesCode":"kineid","comName":"King Eider"},{"speciesCode":"comeid","comName":"Common Eider"},{"speciesCode":"harduc","comName":"Harlequin Duck"},{"speciesCode":"labduc","comName":"Labrador Duck"},{"speciesCode":"sursco","comName":"Surf Scoter"},{"speciesCode":"whwsco2","comName":"White-winged Scoter"},{"speciesCode":"whwsco1","comName":"Stejneger's Scoter"},{"speciesCode":"blksco1","comName":"Common Scoter"},{"speciesCode":"blksco2","comName":"Black Scoter"},{"speciesCode":"lotduc","comName":"Long-tailed Duck"},{"speciesCode":"buffle","comName":"Bufflehead"},{"speciesCode":"comgol","comName":"Common Goldeneye"},{"speciesCode":"bargol","comName":"Barrow's Goldeneye"},{"speciesCode":"smew","comName":"Smew"},{"speciesCode":"hoomer","comName":"Hooded Merganser"},{"speciesCode":"commer","comName":"Common Merganser"},{"speciesCode":"rebmer","comName":"Red-breasted Merganser"},{"speciesCode":"masduc","comName":"Masked Duck"},{"speciesCode":"rudduc","comName":"Ruddy Duck"},{"speciesCode":"placha","comName":"Plain Chachalaca"},{"speciesCode":"helgui","comName":"Helmeted Guineafowl"},{"speciesCode":"mouqua","comName":"Mountain Quail"},{"speciesCode":"norbob","comName":"Northern Bobwhite"},{"speciesCode":"scaqua","comName":"Scaled Quail"},{"speciesCode":"elequa","comName":"Elegant Quail"},{"speciesCode":"calqua","comName":"California Quail"},{"speciesCode":"gamqua","comName":"Gambel's Quail"},{"speciesCode":"monqua","comName":"Montezuma Quail"},{"speciesCode":"wiltur","comName":"Wild Turkey"},{"speciesCode":"rufgro","comName":"Ruffed Grouse"},{"speciesCode":"saggro","comName":"Greater Sage-Grouse"},{"speciesCode":"gusgro","comName":"Gunnison Sage-Grouse"},{"speciesCode":"dusgro","comName":"Dusky Grouse"},{"speciesCode":"soogro1","comName":"Sooty Grouse"},{"speciesCode":"shtgro","comName":"Sharp-tailed Grouse"},{"speciesCode":"grpchi","comName":"Greater Prairie-Chicken"},{"speciesCode":"lepchi","comName":"Lesser Prairie-Chicken"},{"speciesCode":"whtpta1","comName":"White-tailed Ptarmigan"},{"speciesCode":"wilpta","comName":"Willow Ptarmigan"},{"speciesCode":"rocpta1","comName":"Rock Ptarmigan"},{"speciesCode":"sprgro","comName":"Spruce Grouse"},{"speciesCode":"grypar","comName":"Gray Partridge"},{"speciesCode":"golphe","comName":"Golden Pheasant"},{"speciesCode":"rinphe","comName":"Ring-necked Pheasant"},{"speciesCode":"kalphe","comName":"Kalij Pheasant"},{"speciesCode":"silphe","comName":"Silver Pheasant"},{"speciesCode":"compea","comName":"Indian Peafowl"},{"speciesCode":"redjun","comName":"Red Junglefowl"},{"speciesCode":"gryfra","comName":"Gray Francolin"},{"speciesCode":"blkfra","comName":"Black Francolin"},{"speciesCode":"himsno","comName":"Himalayan Snowcock"},{"speciesCode":"blbqua1","comName":"Blue-breasted Quail"},{"speciesCode":"japqua","comName":"Japanese Quail"},{"speciesCode":"chukar","comName":"Chukar"},{"speciesCode":"ercfra","comName":"Erckel's Francolin"},{"speciesCode":"grefla2","comName":"American Flamingo"},{"speciesCode":"grefla3","comName":"Greater Flamingo"},{"speciesCode":"leagre","comName":"Least Grebe"},{"speciesCode":"pibgre","comName":"Pied-billed Grebe"},{"speciesCode":"horgre","comName":"Horned Grebe"},{"speciesCode":"rengre","comName":"Red-necked Grebe"},{"speciesCode":"eargre","comName":"Eared Grebe"},{"speciesCode":"wesgre","comName":"Western Grebe"},{"speciesCode":"clagre","comName":"Clark's Grebe"},{"speciesCode":"rocpig","comName":"Rock Pigeon"},{"speciesCode":"scnpig1","comName":"Scaly-naped Pigeon"},{"speciesCode":"whcpig2","comName":"White-crowned Pigeon"},{"speciesCode":"rebpig1","comName":"Red-billed Pigeon"},{"speciesCode":"batpig1","comName":"Band-tailed Pigeon"},{"speciesCode":"paspig","comName":"Passenger Pigeon"},{"speciesCode":"eutdov","comName":"European Turtle-Dove"},{"speciesCode":"ortdov","comName":"Oriental Turtle-Dove"},{"speciesCode":"eucdov","comName":"Eurasian Collared-Dove"},{"speciesCode":"afcdov1","comName":"African Collared-Dove"},{"speciesCode":"spodov","comName":"Spotted Dove"},{"speciesCode":"diadov1","comName":"Diamond Dove"},{"speciesCode":"zebdov","comName":"Zebra Dove"},{"speciesCode":"incdov","comName":"Inca Dove"},{"speciesCode":"cogdov","comName":"Common Ground Dove"},{"speciesCode":"rugdov","comName":"Ruddy Ground Dove"},{"speciesCode":"ruqdov","comName":"Ruddy Quail-Dove"},{"speciesCode":"kwqdov","comName":"Key West Quail-Dove"},{"speciesCode":"whtdov","comName":"White-tipped Dove"},{"speciesCode":"whwdov","comName":"White-winged Dove"},{"speciesCode":"zendov","comName":"Zenaida Dove"},{"speciesCode":"moudov","comName":"Mourning Dove"},{"speciesCode":"chbsan","comName":"Chestnut-bellied Sandgrouse"},{"speciesCode":"smbani","comName":"Smooth-billed Ani"},{"speciesCode":"grbani","comName":"Groove-billed Ani"},{"speciesCode":"greroa","comName":"Greater Roadrunner"},{"speciesCode":"dabcuc1","comName":"Dark-billed Cuckoo"},{"speciesCode":"yebcuc","comName":"Yellow-billed Cuckoo"},{"speciesCode":"mancuc","comName":"Mangrove Cuckoo"},{"speciesCode":"bkbcuc","comName":"Black-billed Cuckoo"},{"speciesCode":"comcuc","comName":"Common Cuckoo"},{"speciesCode":"oricuc2","comName":"Oriental Cuckoo"},{"speciesCode":"lesnig","comName":"Lesser Nighthawk"},{"speciesCode":"comnig","comName":"Common Nighthawk"},{"speciesCode":"antnig","comName":"Antillean Nighthawk"},{"speciesCode":"compau","comName":"Common Pauraque"},{"speciesCode":"compoo","comName":"Common Poorwill"},{"speciesCode":"chwwid","comName":"Chuck-will's-widow"},{"speciesCode":"bucnig","comName":"Buff-collared Nightjar"},{"speciesCode":"easwpw1","comName":"Eastern Whip-poor-will"},{"speciesCode":"souwpw1","comName":"Mexican Whip-poor-will"},{"speciesCode":"grynig1","comName":"Gray Nightjar"},{"speciesCode":"blkswi","comName":"Black Swift"},{"speciesCode":"whcswi","comName":"White-collared Swift"},{"speciesCode":"chiswi","comName":"Chimney Swift"},{"speciesCode":"vauswi","comName":"Vaux's Swift"},{"speciesCode":"whtnee","comName":"White-throated Needletail"},{"speciesCode":"marswi","comName":"Mariana Swiftlet"},{"speciesCode":"comswi","comName":"Common Swift"},{"speciesCode":"fotswi","comName":"Pacific Swift"},{"speciesCode":"whtswi","comName":"White-throated Swift"},{"speciesCode":"anpswi","comName":"Antillean Palm-Swift"},{"speciesCode":"grnvie1","comName":"Mexican Violetear"},{"speciesCode":"gnbman","comName":"Green-breasted Mango"},{"speciesCode":"maghum1","comName":"Rivoli's Hummingbird"},{"speciesCode":"plcsta","comName":"Plain-capped Starthroat"},{"speciesCode":"amthum1","comName":"Amethyst-throated Mountain-gem"},{"speciesCode":"buthum","comName":"Blue-throated Mountain-gem"},{"speciesCode":"luchum","comName":"Lucifer Hummingbird"},{"speciesCode":"rthhum","comName":"Ruby-throated Hummingbird"},{"speciesCode":"bkchum","comName":"Black-chinned Hummingbird"},{"speciesCode":"bahwoo","comName":"Bahama Woodstar"},{"speciesCode":"annhum","comName":"Anna's Hummingbird"},{"speciesCode":"coshum","comName":"Costa's Hummingbird"},{"speciesCode":"calhum","comName":"Calliope Hummingbird"},{"speciesCode":"rufhum","comName":"Rufous Hummingbird"},{"speciesCode":"allhum","comName":"Allen's Hummingbird"},{"speciesCode":"brthum","comName":"Broad-tailed Hummingbird"},{"speciesCode":"brbhum","comName":"Broad-billed Hummingbird"},{"speciesCode":"whehum","comName":"White-eared Hummingbird"},{"speciesCode":"xanhum","comName":"Xantus's Hummingbird"},{"speciesCode":"vichum","comName":"Violet-crowned Hummingbird"},{"speciesCode":"berhum","comName":"Berylline Hummingbird"},{"speciesCode":"cinhum1","comName":"Cinnamon Hummingbird"},{"speciesCode":"bubhum","comName":"Buff-bellied Hummingbird"},{"speciesCode":"ridrai1","comName":"Ridgway's Rail"},{"speciesCode":"kinrai4","comName":"King Rail"},{"speciesCode":"clarai11","comName":"Clapper Rail"},{"speciesCode":"virrai","comName":"Virginia Rail"},{"speciesCode":"corcra","comName":"Corn Crake"},{"speciesCode":"pabcra","comName":"Paint-billed Crake"},{"speciesCode":"sporai","comName":"Spotted Rail"},{"speciesCode":"rnwrai1","comName":"Rufous-necked Wood-Rail"},{"speciesCode":"sora","comName":"Sora"},{"speciesCode":"commoo3","comName":"Eurasian Moorhen"},{"speciesCode":"comgal1","comName":"Common Gallinule"},{"speciesCode":"eurcoo","comName":"Eurasian Coot"},{"speciesCode":"hawcoo","comName":"Hawaiian Coot"},{"speciesCode":"y00475","comName":"American Coot"},{"speciesCode":"purgal2","comName":"Purple Gallinule"},{"speciesCode":"azugal1","comName":"Azure Gallinule"},{"speciesCode":"purswa3","comName":"Gray-headed Swamphen"},{"speciesCode":"baicra1","comName":"Baillon's Crake"},{"speciesCode":"yelrai","comName":"Yellow Rail"},{"speciesCode":"blkrai","comName":"Black Rail"},{"speciesCode":"sungre1","comName":"Sungrebe"},{"speciesCode":"limpki","comName":"Limpkin"},{"speciesCode":"demcra1","comName":"Demoiselle Crane"},{"speciesCode":"sancra","comName":"Sandhill Crane"},{"speciesCode":"comcra","comName":"Common Crane"},{"speciesCode":"hoocra1","comName":"Hooded Crane"},{"speciesCode":"whocra","comName":"Whooping Crane"},{"speciesCode":"dstkne","comName":"Double-striped Thick-knee"},{"speciesCode":"bkwsti","comName":"Black-winged Stilt"},{"speciesCode":"bknsti","comName":"Black-necked Stilt"},{"speciesCode":"ameavo","comName":"American Avocet"},{"speciesCode":"euroys1","comName":"Eurasian Oystercatcher"},{"speciesCode":"ameoys","comName":"American Oystercatcher"},{"speciesCode":"blkoys","comName":"Black Oystercatcher"},{"speciesCode":"bkbplo","comName":"Black-bellied Plover"},{"speciesCode":"eugplo","comName":"European Golden-Plover"},{"speciesCode":"amgplo","comName":"American Golden-Plover"},{"speciesCode":"pagplo","comName":"Pacific Golden-Plover"},{"speciesCode":"norlap","comName":"Northern Lapwing"},{"speciesCode":"soulap1","comName":"Southern Lapwing"},{"speciesCode":"lesplo","comName":"Lesser Sand-Plover"},{"speciesCode":"grsplo","comName":"Greater Sand-Plover"},{"speciesCode":"colplo1","comName":"Collared Plover"},{"speciesCode":"snoplo5","comName":"Snowy Plover"},{"speciesCode":"wilplo","comName":"Wilson's Plover"},{"speciesCode":"corplo","comName":"Common Ringed Plover"},{"speciesCode":"semplo","comName":"Semipalmated Plover"},{"speciesCode":"pipplo","comName":"Piping Plover"},{"speciesCode":"lirplo","comName":"Little Ringed Plover"},{"speciesCode":"killde","comName":"Killdeer"},{"speciesCode":"mouplo","comName":"Mountain Plover"},{"speciesCode":"eurdot","comName":"Eurasian Dotterel"},{"speciesCode":"norjac","comName":"Northern Jacana"},{"speciesCode":"uplsan","comName":"Upland Sandpiper"},{"speciesCode":"brtcur","comName":"Bristle-thighed Curlew"},{"speciesCode":"whimbr","comName":"Whimbrel"},{"speciesCode":"litcur","comName":"Little Curlew"},{"speciesCode":"eskcur","comName":"Eskimo Curlew"},{"speciesCode":"lobcur","comName":"Long-billed Curlew"},{"speciesCode":"faecur","comName":"Far Eastern Curlew"},{"speciesCode":"eurcur","comName":"Eurasian Curlew"},{"speciesCode":"batgod","comName":"Bar-tailed Godwit"},{"speciesCode":"bktgod","comName":"Black-tailed Godwit"},{"speciesCode":"hudgod","comName":"Hudsonian Godwit"},{"speciesCode":"margod","comName":"Marbled Godwit"},{"speciesCode":"rudtur","comName":"Ruddy Turnstone"},{"speciesCode":"blktur","comName":"Black Turnstone"},{"speciesCode":"grekno","comName":"Great Knot"},{"speciesCode":"redkno","comName":"Red Knot"},{"speciesCode":"surfbi","comName":"Surfbird"},{"speciesCode":"ruff","comName":"Ruff"},{"speciesCode":"brbsan","comName":"Broad-billed Sandpiper"},{"speciesCode":"shtsan","comName":"Sharp-tailed Sandpiper"},{"speciesCode":"stisan","comName":"Stilt Sandpiper"},{"speciesCode":"cursan","comName":"Curlew Sandpiper"},{"speciesCode":"temsti","comName":"Temminck's Stint"},{"speciesCode":"lotsti","comName":"Long-toed Stint"},{"speciesCode":"spbsan1","comName":"Spoon-billed Sandpiper"},{"speciesCode":"rensti","comName":"Red-necked Stint"},{"speciesCode":"sander","comName":"Sanderling"},{"speciesCode":"dunlin","comName":"Dunlin"},{"speciesCode":"rocsan","comName":"Rock Sandpiper"},{"speciesCode":"pursan","comName":"Purple Sandpiper"},{"speciesCode":"baisan","comName":"Baird's Sandpiper"},{"speciesCode":"litsti","comName":"Little Stint"},{"speciesCode":"leasan","comName":"Least Sandpiper"},{"speciesCode":"whrsan","comName":"White-rumped Sandpiper"},{"speciesCode":"bubsan","comName":"Buff-breasted Sandpiper"},{"speciesCode":"pecsan","comName":"Pectoral Sandpiper"},{"speciesCode":"semsan","comName":"Semipalmated Sandpiper"},{"speciesCode":"wessan","comName":"Western Sandpiper"},{"speciesCode":"shbdow","comName":"Short-billed Dowitcher"},{"speciesCode":"lobdow","comName":"Long-billed Dowitcher"},{"speciesCode":"jacsni","comName":"Jack Snipe"},{"speciesCode":"eurwoo","comName":"Eurasian Woodcock"},{"speciesCode":"amewoo","comName":"American Woodcock"},{"speciesCode":"solsni1","comName":"Solitary Snipe"},{"speciesCode":"comsni","comName":"Common Snipe"},{"speciesCode":"wilsni1","comName":"Wilson's Snipe"},{"speciesCode":"pitsni","comName":"Pin-tailed Snipe"},{"speciesCode":"tersan","comName":"Terek Sandpiper"},{"speciesCode":"wilpha","comName":"Wilson's Phalarope"},{"speciesCode":"renpha","comName":"Red-necked Phalarope"},{"speciesCode":"redpha1","comName":"Red Phalarope"},{"speciesCode":"comsan","comName":"Common Sandpiper"},{"speciesCode":"sposan","comName":"Spotted Sandpiper"},{"speciesCode":"grnsan","comName":"Green Sandpiper"},{"speciesCode":"solsan","comName":"Solitary Sandpiper"},{"speciesCode":"gyttat1","comName":"Gray-tailed Tattler"},{"speciesCode":"wantat1","comName":"Wandering Tattler"},{"speciesCode":"spored","comName":"Spotted Redshank"},{"speciesCode":"greyel","comName":"Greater Yellowlegs"},{"speciesCode":"comgre","comName":"Common Greenshank"},{"speciesCode":"willet1","comName":"Willet"},{"speciesCode":"lesyel","comName":"Lesser Yellowlegs"},{"speciesCode":"marsan","comName":"Marsh Sandpiper"},{"speciesCode":"woosan","comName":"Wood Sandpiper"},{"speciesCode":"oripra","comName":"Oriental Pratincole"},{"speciesCode":"gresku1","comName":"Great Skua"},{"speciesCode":"sopsku1","comName":"South Polar Skua"},{"speciesCode":"pomjae","comName":"Pomarine Jaeger"},{"speciesCode":"parjae","comName":"Parasitic Jaeger"},{"speciesCode":"lotjae","comName":"Long-tailed Jaeger"},{"speciesCode":"doveki","comName":"Dovekie"},{"speciesCode":"commur","comName":"Common Murre"},{"speciesCode":"thbmur","comName":"Thick-billed Murre"},{"speciesCode":"razorb","comName":"Razorbill"},{"speciesCode":"blkgui","comName":"Black Guillemot"},{"speciesCode":"piggui","comName":"Pigeon Guillemot"},{"speciesCode":"lobmur","comName":"Long-billed Murrelet"},{"speciesCode":"marmur","comName":"Marbled Murrelet"},{"speciesCode":"kitmur","comName":"Kittlitz's Murrelet"},{"speciesCode":"xanmur2","comName":"Scripps's Murrelet"},{"speciesCode":"xanmur1","comName":"Guadalupe Murrelet"},{"speciesCode":"cramur","comName":"Craveri's Murrelet"},{"speciesCode":"ancmur","comName":"Ancient Murrelet"},{"speciesCode":"casauk","comName":"Cassin's Auklet"},{"speciesCode":"parauk","comName":"Parakeet Auklet"},{"speciesCode":"leaauk","comName":"Least Auklet"},{"speciesCode":"whiauk","comName":"Whiskered Auklet"},{"speciesCode":"creauk","comName":"Crested Auklet"},{"speciesCode":"rhiauk","comName":"Rhinoceros Auklet"},{"speciesCode":"atlpuf","comName":"Atlantic Puffin"},{"speciesCode":"horpuf","comName":"Horned Puffin"},{"speciesCode":"tufpuf","comName":"Tufted Puffin"},{"speciesCode":"swtgul1","comName":"Swallow-tailed Gull"},{"speciesCode":"bklkit","comName":"Black-legged Kittiwake"},{"speciesCode":"relkit","comName":"Red-legged Kittiwake"},{"speciesCode":"ivogul","comName":"Ivory Gull"},{"speciesCode":"sabgul","comName":"Sabine's Gull"},{"speciesCode":"bongul","comName":"Bonaparte's Gull"},{"speciesCode":"grhgul","comName":"Gray-hooded Gull"},{"speciesCode":"bkhgul","comName":"Black-headed Gull"},{"speciesCode":"litgul","comName":"Little Gull"},{"speciesCode":"rosgul","comName":"Ross's Gull"},{"speciesCode":"laugul","comName":"Laughing Gull"},{"speciesCode":"fragul","comName":"Franklin's Gull"},{"speciesCode":"gbhgul2","comName":"Pallas's Gull"},{"speciesCode":"belgul","comName":"Belcher's Gull"},{"speciesCode":"bktgul","comName":"Black-tailed Gull"},{"speciesCode":"heegul","comName":"Heermann's Gull"},{"speciesCode":"mewgul","comName":"Common Gull"},{"speciesCode":"mewgul2","comName":"Short-billed Gull"},{"speciesCode":"ribgul","comName":"Ring-billed Gull"},{"speciesCode":"wesgul","comName":"Western Gull"},{"speciesCode":"yefgul","comName":"Yellow-footed Gull"},{"speciesCode":"calgul","comName":"California Gull"},{"speciesCode":"hergul","comName":"Herring Gull"},{"speciesCode":"yelgul1","comName":"Yellow-legged Gull"},{"speciesCode":"y00478","comName":"Iceland Gull"},{"speciesCode":"lbbgul","comName":"Lesser Black-backed Gull"},{"speciesCode":"slbgul","comName":"Slaty-backed Gull"},{"speciesCode":"glwgul","comName":"Glaucous-winged Gull"},{"speciesCode":"glagul","comName":"Glaucous Gull"},{"speciesCode":"gbbgul","comName":"Great Black-backed Gull"},{"speciesCode":"kelgul","comName":"Kelp Gull"},{"speciesCode":"brnnod","comName":"Brown Noddy"},{"speciesCode":"blknod","comName":"Black Noddy"},{"speciesCode":"bugnod","comName":"Blue-gray Noddy"},{"speciesCode":"whiter","comName":"White Tern"},{"speciesCode":"sooter1","comName":"Sooty Tern"},{"speciesCode":"gybter1","comName":"Gray-backed Tern"},{"speciesCode":"briter1","comName":"Bridled Tern"},{"speciesCode":"aleter1","comName":"Aleutian Tern"},{"speciesCode":"leater1","comName":"Least Tern"},{"speciesCode":"labter1","comName":"Large-billed Tern"},{"speciesCode":"gubter1","comName":"Gull-billed Tern"},{"speciesCode":"caster1","comName":"Caspian Tern"},{"speciesCode":"incter1","comName":"Inca Tern"},{"speciesCode":"blkter","comName":"Black Tern"},{"speciesCode":"whwter","comName":"White-winged Tern"},{"speciesCode":"whiter2","comName":"Whiskered Tern"},{"speciesCode":"roster","comName":"Roseate Tern"},{"speciesCode":"comter","comName":"Common Tern"},{"speciesCode":"arcter","comName":"Arctic Tern"},{"speciesCode":"forter","comName":"Forster's Tern"},{"speciesCode":"royter1","comName":"Royal Tern"},{"speciesCode":"grcter1","comName":"Great Crested Tern"},{"speciesCode":"santer1","comName":"Sandwich Tern"},{"speciesCode":"eleter1","comName":"Elegant Tern"},{"speciesCode":"blkski","comName":"Black Skimmer"},{"speciesCode":"whttro","comName":"White-tailed Tropicbird"},{"speciesCode":"rebtro","comName":"Red-billed Tropicbird"},{"speciesCode":"rettro","comName":"Red-tailed Tropicbird"},{"speciesCode":"retloo","comName":"Red-throated Loon"},{"speciesCode":"arcloo","comName":"Arctic Loon"},{"speciesCode":"pacloo","comName":"Pacific Loon"},{"speciesCode":"comloo","comName":"Common Loon"},{"speciesCode":"yebloo","comName":"Yellow-billed Loon"},{"speciesCode":"yenalb","comName":"Yellow-nosed Albatross"},{"speciesCode":"whcalb1","comName":"White-capped Albatross"},{"speciesCode":"salalb1","comName":"Salvin's Albatross"},{"speciesCode":"shyalb2","comName":"Chatham Albatross"},{"speciesCode":"bkbalb","comName":"Black-browed Albatross"},{"speciesCode":"limalb1","comName":"Light-mantled Albatross"},{"speciesCode":"wanalb","comName":"Wandering Albatross"},{"speciesCode":"layalb","comName":"Laysan Albatross"},{"speciesCode":"bkfalb","comName":"Black-footed Albatross"},{"speciesCode":"shtalb","comName":"Short-tailed Albatross"},{"speciesCode":"wispet","comName":"Wilson's Storm-Petrel"},{"speciesCode":"wfspet","comName":"White-faced Storm-Petrel"},{"speciesCode":"bbspet1","comName":"Black-bellied Storm-Petrel"},{"speciesCode":"bripet","comName":"European Storm-Petrel"},{"speciesCode":"ftspet","comName":"Fork-tailed Storm-Petrel"},{"speciesCode":"rispet1","comName":"Ringed Storm-Petrel"},{"speciesCode":"lcspet","comName":"Leach's Storm-Petrel"},{"speciesCode":"leastp5","comName":"Townsend's Storm-Petrel"},{"speciesCode":"swspet","comName":"Swinhoe's Storm-Petrel"},{"speciesCode":"asspet","comName":"Ashy Storm-Petrel"},{"speciesCode":"barpet","comName":"Band-rumped Storm-Petrel"},{"speciesCode":"wrspet","comName":"Wedge-rumped Storm-Petrel"},{"speciesCode":"bkspet","comName":"Black Storm-Petrel"},{"speciesCode":"trspet","comName":"Tristram's Storm-Petrel"},{"speciesCode":"lsspet","comName":"Least Storm-Petrel"},{"speciesCode":"norgip1","comName":"Northern Giant-Petrel"},{"speciesCode":"norful","comName":"Northern Fulmar"},{"speciesCode":"grwpet2","comName":"Gray-faced Petrel"},{"speciesCode":"kerpet","comName":"Kermadec Petrel"},{"speciesCode":"tripet1","comName":"Trindade Petrel"},{"speciesCode":"herpet2","comName":"Herald Petrel"},{"speciesCode":"murpet","comName":"Murphy's Petrel"},{"speciesCode":"solpet1","comName":"Providence Petrel"},{"speciesCode":"madpet","comName":"Zino's Petrel"},{"speciesCode":"feapet1","comName":"Fea's Petrel"},{"speciesCode":"motpet","comName":"Mottled Petrel"},{"speciesCode":"berpet","comName":"Bermuda Petrel"},{"speciesCode":"bkcpet","comName":"Black-capped Petrel"},{"speciesCode":"jufpet","comName":"Juan Fernandez Petrel"},{"speciesCode":"hawpet1","comName":"Hawaiian Petrel"},{"speciesCode":"whnpet","comName":"White-necked Petrel"},{"speciesCode":"bonpet","comName":"Bonin Petrel"},{"speciesCode":"bkwpet","comName":"Black-winged Petrel"},{"speciesCode":"coopet","comName":"Cook's Petrel"},{"speciesCode":"stepet","comName":"Stejneger's Petrel"},{"speciesCode":"bulpet","comName":"Bulwer's Petrel"},{"speciesCode":"joupet","comName":"Jouanin's Petrel"},{"speciesCode":"tahpet1","comName":"Tahiti Petrel"},{"speciesCode":"whcpet1","comName":"White-chinned Petrel"},{"speciesCode":"parpet1","comName":"Parkinson's Petrel"},{"speciesCode":"strshe","comName":"Streaked Shearwater"},{"speciesCode":"corshe","comName":"Cory's Shearwater"},{"speciesCode":"cavshe1","comName":"Cape Verde Shearwater"},{"speciesCode":"pifshe","comName":"Pink-footed Shearwater"},{"speciesCode":"flfshe","comName":"Flesh-footed Shearwater"},{"speciesCode":"greshe","comName":"Great Shearwater"},{"speciesCode":"wetshe","comName":"Wedge-tailed Shearwater"},{"speciesCode":"bulshe","comName":"Buller's Shearwater"},{"speciesCode":"sooshe","comName":"Sooty Shearwater"},{"speciesCode":"shtshe","comName":"Short-tailed Shearwater"},{"speciesCode":"chrshe","comName":"Christmas Shearwater"},{"speciesCode":"manshe","comName":"Manx Shearwater"},{"speciesCode":"towshe2","comName":"Newell's Shearwater"},{"speciesCode":"bkvshe","comName":"Black-vented Shearwater"},{"speciesCode":"litshe1","comName":"Barolo Shearwater"},{"speciesCode":"audshe","comName":"Audubon's Shearwater"},{"speciesCode":"wonsto1","comName":"Woolly-necked Stork"},{"speciesCode":"blnsto1","comName":"Black-necked Stork"},{"speciesCode":"jabiru","comName":"Jabiru"},{"speciesCode":"woosto","comName":"Wood Stork"},{"speciesCode":"lesfri","comName":"Lesser Frigatebird"},{"speciesCode":"magfri","comName":"Magnificent Frigatebird"},{"speciesCode":"grefri","comName":"Great Frigatebird"},{"speciesCode":"masboo","comName":"Masked Booby"},{"speciesCode":"nazboo1","comName":"Nazca Booby"},{"speciesCode":"bfoboo","comName":"Blue-footed Booby"},{"speciesCode":"brnboo","comName":"Brown Booby"},{"speciesCode":"refboo","comName":"Red-footed Booby"},{"speciesCode":"norgan","comName":"Northern Gannet"},{"speciesCode":"anhing","comName":"Anhinga"},{"speciesCode":"bracor","comName":"Brandt's Cormorant"},{"speciesCode":"refcor","comName":"Red-faced Cormorant"},{"speciesCode":"pelcor","comName":"Pelagic Cormorant"},{"speciesCode":"grecor","comName":"Great Cormorant"},{"speciesCode":"doccor","comName":"Double-crested Cormorant"},{"speciesCode":"neocor","comName":"Neotropic Cormorant"},{"speciesCode":"amwpel","comName":"American White Pelican"},{"speciesCode":"brnpel","comName":"Brown Pelican"},{"speciesCode":"pibpel1","comName":"Pink-backed Pelican"},{"speciesCode":"amebit","comName":"American Bittern"},{"speciesCode":"grebit1","comName":"Great Bittern"},{"speciesCode":"yelbit","comName":"Yellow Bittern"},{"speciesCode":"leabit","comName":"Least Bittern"},{"speciesCode":"btther1","comName":"Bare-throated Tiger-Heron"},{"speciesCode":"grbher3","comName":"Great Blue Heron"},{"speciesCode":"graher1","comName":"Gray Heron"},{"speciesCode":"greegr","comName":"Great Egret"},{"speciesCode":"integr","comName":"Intermediate Egret"},{"speciesCode":"chiegr","comName":"Chinese Egret"},{"speciesCode":"litegr","comName":"Little Egret"},{"speciesCode":"werher","comName":"Western Reef-Heron"},{"speciesCode":"snoegr","comName":"Snowy Egret"},{"speciesCode":"libher","comName":"Little Blue Heron"},{"speciesCode":"triher","comName":"Tricolored Heron"},{"speciesCode":"redegr","comName":"Reddish Egret"},{"speciesCode":"categr","comName":"Cattle Egret"},{"speciesCode":"chpher1","comName":"Chinese Pond-Heron"},{"speciesCode":"grnher","comName":"Green Heron"},{"speciesCode":"bcnher","comName":"Black-crowned Night-Heron"},{"speciesCode":"ycnher","comName":"Yellow-crowned Night-Heron"},{"speciesCode":"whiibi","comName":"White Ibis"},{"speciesCode":"gloibi","comName":"Glossy Ibis"},{"speciesCode":"whfibi","comName":"White-faced Ibis"},{"speciesCode":"sacibi2","comName":"African Sacred Ibis"},{"speciesCode":"rosspo1","comName":"Roseate Spoonbill"},{"speciesCode":"calcon","comName":"California Condor"},{"speciesCode":"blkvul","comName":"Black Vulture"},{"speciesCode":"turvul","comName":"Turkey Vulture"},{"speciesCode":"osprey","comName":"Osprey"},{"speciesCode":"whtkit","comName":"White-tailed Kite"},{"speciesCode":"hobkit","comName":"Hook-billed Kite"},{"speciesCode":"swtkit","comName":"Swallow-tailed Kite"},{"speciesCode":"goleag","comName":"Golden Eagle"},{"speciesCode":"snakit","comName":"Snail Kite"},{"speciesCode":"dotkit1","comName":"Double-toothed Kite"},{"speciesCode":"miskit","comName":"Mississippi Kite"},{"speciesCode":"wemhar1","comName":"Eurasian Marsh-Harrier"},{"speciesCode":"norhar1","comName":"Hen Harrier"},{"speciesCode":"norhar2","comName":"Northern Harrier"},{"speciesCode":"grfhaw1","comName":"Chinese Sparrowhawk"},{"speciesCode":"eurspa1","comName":"Eurasian Sparrowhawk"},{"speciesCode":"shshaw","comName":"Sharp-shinned Hawk"},{"speciesCode":"coohaw","comName":"Cooper's Hawk"},{"speciesCode":"norgos","comName":"Northern Goshawk"},{"speciesCode":"blakit1","comName":"Black Kite"},{"speciesCode":"baleag","comName":"Bald Eagle"},{"speciesCode":"whteag","comName":"White-tailed Eagle"},{"speciesCode":"stseag","comName":"Steller's Sea-Eagle"},{"speciesCode":"crahaw","comName":"Crane Hawk"},{"speciesCode":"comblh1","comName":"Common Black Hawk"},{"speciesCode":"grbhaw1","comName":"Great Black Hawk"},{"speciesCode":"roahaw","comName":"Roadside Hawk"},{"speciesCode":"hrshaw","comName":"Harris's Hawk"},{"speciesCode":"whthaw","comName":"White-tailed Hawk"},{"speciesCode":"rebhaw2","comName":"Variable Hawk"},{"speciesCode":"gryhaw2","comName":"Gray Hawk"},{"speciesCode":"reshaw","comName":"Red-shouldered Hawk"},{"speciesCode":"brwhaw","comName":"Broad-winged Hawk"},{"speciesCode":"hawhaw","comName":"Hawaiian Hawk"},{"speciesCode":"shthaw","comName":"Short-tailed Hawk"},{"speciesCode":"swahaw","comName":"Swainson's Hawk"},{"speciesCode":"zothaw","comName":"Zone-tailed Hawk"},{"speciesCode":"rethaw","comName":"Red-tailed Hawk"},{"speciesCode":"rolhaw","comName":"Rough-legged Hawk"},{"speciesCode":"ferhaw","comName":"Ferruginous Hawk"},{"speciesCode":"combuz1","comName":"Common Buzzard"},{"speciesCode":"lolbuz1","comName":"Long-legged Buzzard"},{"speciesCode":"brnowl","comName":"Barn Owl"},{"speciesCode":"orsowl","comName":"Oriental Scops-Owl"},{"speciesCode":"flaowl","comName":"Flammulated Owl"},{"speciesCode":"whsowl1","comName":"Whiskered Screech-Owl"},{"speciesCode":"wesowl1","comName":"Western Screech-Owl"},{"speciesCode":"easowl1","comName":"Eastern Screech-Owl"},{"speciesCode":"grhowl","comName":"Great Horned Owl"},{"speciesCode":"snoowl1","comName":"Snowy Owl"},{"speciesCode":"nohowl","comName":"Northern Hawk Owl"},{"speciesCode":"nopowl","comName":"Northern Pygmy-Owl"},{"speciesCode":"fepowl","comName":"Ferruginous Pygmy-Owl"},{"speciesCode":"elfowl","comName":"Elf Owl"},{"speciesCode":"burowl","comName":"Burrowing Owl"},{"speciesCode":"motowl","comName":"Mottled Owl"},{"speciesCode":"spoowl","comName":"Spotted Owl"},{"speciesCode":"brdowl","comName":"Barred Owl"},{"speciesCode":"grgowl","comName":"Great Gray Owl"},{"speciesCode":"loeowl","comName":"Long-eared Owl"},{"speciesCode":"styowl1","comName":"Stygian Owl"},{"speciesCode":"sheowl","comName":"Short-eared Owl"},{"speciesCode":"borowl","comName":"Boreal Owl"},{"speciesCode":"nswowl","comName":"Northern Saw-whet Owl"},{"speciesCode":"norboo1","comName":"Northern Boobook"},{"speciesCode":"earque","comName":"Eared Quetzal"},{"speciesCode":"eletro","comName":"Elegant Trogon"},{"speciesCode":"hoopoe","comName":"Eurasian Hoopoe"},{"speciesCode":"rinkin1","comName":"Ringed Kingfisher"},{"speciesCode":"belkin1","comName":"Belted Kingfisher"},{"speciesCode":"amakin1","comName":"Amazon Kingfisher"},{"speciesCode":"grnkin","comName":"Green Kingfisher"},{"speciesCode":"eurwry","comName":"Eurasian Wryneck"},{"speciesCode":"wilsap","comName":"Williamson's Sapsucker"},{"speciesCode":"yebsap","comName":"Yellow-bellied Sapsucker"},{"speciesCode":"rensap","comName":"Red-naped Sapsucker"},{"speciesCode":"rebsap","comName":"Red-breasted Sapsucker"},{"speciesCode":"lewwoo","comName":"Lewis's Woodpecker"},{"speciesCode":"rehwoo","comName":"Red-headed Woodpecker"},{"speciesCode":"acowoo","comName":"Acorn Woodpecker"},{"speciesCode":"gilwoo","comName":"Gila Woodpecker"},{"speciesCode":"gofwoo","comName":"Golden-fronted Woodpecker"},{"speciesCode":"rebwoo","comName":"Red-bellied Woodpecker"},{"speciesCode":"attwoo1","comName":"American Three-toed Woodpecker"},{"speciesCode":"bkbwoo","comName":"Black-backed Woodpecker"},{"speciesCode":"grswoo","comName":"Great Spotted Woodpecker"},{"speciesCode":"dowwoo","comName":"Downy Woodpecker"},{"speciesCode":"nutwoo","comName":"Nuttall's Woodpecker"},{"speciesCode":"labwoo","comName":"Ladder-backed Woodpecker"},{"speciesCode":"recwoo","comName":"Red-cockaded Woodpecker"},{"speciesCode":"haiwoo","comName":"Hairy Woodpecker"},{"speciesCode":"whhwoo","comName":"White-headed Woodpecker"},{"speciesCode":"ariwoo","comName":"Arizona Woodpecker"},{"speciesCode":"ivbwoo","comName":"Ivory-billed Woodpecker"},{"speciesCode":"pilwoo","comName":"Pileated Woodpecker"},{"speciesCode":"norfli","comName":"Northern Flicker"},{"speciesCode":"gilfli","comName":"Gilded Flicker"},{"speciesCode":"coffal1","comName":"Collared Forest-Falcon"},{"speciesCode":"y00678","comName":"Crested Caracara"},{"speciesCode":"eurkes","comName":"Eurasian Kestrel"},{"speciesCode":"amekes","comName":"American Kestrel"},{"speciesCode":"reffal1","comName":"Red-footed Falcon"},{"speciesCode":"merlin","comName":"Merlin"},{"speciesCode":"eurhob","comName":"Eurasian Hobby"},{"speciesCode":"aplfal","comName":"Aplomado Falcon"},{"speciesCode":"gyrfal","comName":"Gyrfalcon"},{"speciesCode":"perfal","comName":"Peregrine Falcon"},{"speciesCode":"prafal","comName":"Prairie Falcon"},{"speciesCode":"tancoc1","comName":"Tanimbar Corella"},{"speciesCode":"succoc","comName":"Sulphur-crested Cockatoo"},{"speciesCode":"saccoc","comName":"Salmon-crested Cockatoo"},{"speciesCode":"whicoc1","comName":"White Cockatoo"},{"speciesCode":"cockat","comName":"Cockatiel"},{"speciesCode":"rorpar","comName":"Rose-ringed Parakeet"},{"speciesCode":"plhpar1","comName":"Plum-headed Parakeet"},{"speciesCode":"budger","comName":"Budgerigar"},{"speciesCode":"peflov","comName":"Rosy-faced Lovebird"},{"speciesCode":"fislov1","comName":"Fischer's Lovebird"},{"speciesCode":"yeclov","comName":"Yellow-collared Lovebird"},{"speciesCode":"monpar","comName":"Monk Parakeet"},{"speciesCode":"whwpar","comName":"White-winged Parakeet"},{"speciesCode":"yecpar","comName":"Yellow-chevroned Parakeet"},{"speciesCode":"schpar1","comName":"Scaly-headed Parrot"},{"speciesCode":"blhpar1","comName":"Blue-headed Parrot"},{"speciesCode":"recpar","comName":"Red-crowned Parrot"},{"speciesCode":"licpar","comName":"Lilac-crowned Parrot"},{"speciesCode":"relpar","comName":"Red-lored Parrot"},{"speciesCode":"yehpar","comName":"Yellow-headed Parrot"},{"speciesCode":"ywcpar","comName":"Yellow-crowned Parrot"},{"speciesCode":"bufpar","comName":"Turquoise-fronted Parrot"},{"speciesCode":"whfpar1","comName":"White-fronted Parrot"},{"speciesCode":"meapar","comName":"Mealy Parrot"},{"speciesCode":"orwpar","comName":"Orange-winged Parrot"},{"speciesCode":"burpar","comName":"Burrowing Parakeet"},{"speciesCode":"thbpar","comName":"Thick-billed Parrot"},{"speciesCode":"carpar","comName":"Carolina Parakeet"},{"speciesCode":"duhpar","comName":"Dusky-headed Parakeet"},{"speciesCode":"bkhpar","comName":"Nanday Parakeet"},{"speciesCode":"sunpar1","comName":"Sun Parakeet"},{"speciesCode":"baymac","comName":"Blue-and-yellow Macaw"},{"speciesCode":"chfmac1","comName":"Chestnut-fronted Macaw"},{"speciesCode":"bucpar","comName":"Blue-crowned Parakeet"},{"speciesCode":"grnpar","comName":"Green Parakeet"},{"speciesCode":"crfpar","comName":"Crimson-fronted Parakeet"},{"speciesCode":"scfpar1","comName":"Scarlet-fronted Parakeet"},{"speciesCode":"mitpar","comName":"Mitred Parakeet"},{"speciesCode":"rempar","comName":"Red-masked Parakeet"},{"speciesCode":"whepar2","comName":"White-eyed Parakeet"},{"speciesCode":"mastit1","comName":"Masked Tityra"},{"speciesCode":"grcbec1","comName":"Gray-collared Becard"},{"speciesCode":"rotbec","comName":"Rose-throated Becard"},{"speciesCode":"nobtyr","comName":"Northern Beardless-Tyrannulet"},{"speciesCode":"greela","comName":"Greenish Elaenia"},{"speciesCode":"smbela1","comName":"Small-billed Elaenia"},{"speciesCode":"whcela1","comName":"White-crested Elaenia"},{"speciesCode":"tuffly","comName":"Tufted Flycatcher"},{"speciesCode":"olsfly","comName":"Olive-sided Flycatcher"},{"speciesCode":"grepew","comName":"Greater Pewee"},{"speciesCode":"wewpew","comName":"Western Wood-Pewee"},{"speciesCode":"eawpew","comName":"Eastern Wood-Pewee"},{"speciesCode":"cubpew1","comName":"Cuban Pewee"},{"speciesCode":"yebfly","comName":"Yellow-bellied Flycatcher"},{"speciesCode":"acafly","comName":"Acadian Flycatcher"},{"speciesCode":"aldfly","comName":"Alder Flycatcher"},{"speciesCode":"wilfly","comName":"Willow Flycatcher"},{"speciesCode":"leafly","comName":"Least Flycatcher"},{"speciesCode":"hamfly","comName":"Hammond's Flycatcher"},{"speciesCode":"gryfly","comName":"Gray Flycatcher"},{"speciesCode":"dusfly","comName":"Dusky Flycatcher"},{"speciesCode":"pinfly1","comName":"Pine Flycatcher"},{"speciesCode":"pasfly","comName":"Pacific-slope Flycatcher"},{"speciesCode":"corfly","comName":"Cordilleran Flycatcher"},{"speciesCode":"bubfly","comName":"Buff-breasted Flycatcher"},{"speciesCode":"blkpho","comName":"Black Phoebe"},{"speciesCode":"easpho","comName":"Eastern Phoebe"},{"speciesCode":"saypho","comName":"Say's Phoebe"},{"speciesCode":"verfly","comName":"Vermilion Flycatcher"},{"speciesCode":"ducfly","comName":"Dusky-capped Flycatcher"},{"speciesCode":"astfly","comName":"Ash-throated Flycatcher"},{"speciesCode":"nutfly","comName":"Nutting's Flycatcher"},{"speciesCode":"grcfly","comName":"Great Crested Flycatcher"},{"speciesCode":"bncfly","comName":"Brown-crested Flycatcher"},{"speciesCode":"lasfly","comName":"La Sagra's Flycatcher"},{"speciesCode":"grekis","comName":"Great Kiskadee"},{"speciesCode":"socfly1","comName":"Social Flycatcher"},{"speciesCode":"subfly","comName":"Sulphur-bellied Flycatcher"},{"speciesCode":"pirfly1","comName":"Piratic Flycatcher"},{"speciesCode":"varfly","comName":"Variegated Flycatcher"},{"speciesCode":"croslf1","comName":"Crowned Slaty Flycatcher"},{"speciesCode":"trokin","comName":"Tropical Kingbird"},{"speciesCode":"coukin","comName":"Couch's Kingbird"},{"speciesCode":"caskin","comName":"Cassin's Kingbird"},{"speciesCode":"thbkin","comName":"Thick-billed Kingbird"},{"speciesCode":"weskin","comName":"Western Kingbird"},{"speciesCode":"easkin","comName":"Eastern Kingbird"},{"speciesCode":"grykin","comName":"Gray Kingbird"},{"speciesCode":"logkin","comName":"Loggerhead Kingbird"},{"speciesCode":"sctfly","comName":"Scissor-tailed Flycatcher"},{"speciesCode":"fotfly","comName":"Fork-tailed Flycatcher"},{"speciesCode":"bkcvir1","comName":"Black-capped Vireo"},{"speciesCode":"whevir","comName":"White-eyed Vireo"},{"speciesCode":"thbvir","comName":"Thick-billed Vireo"},{"speciesCode":"cubvir1","comName":"Cuban Vireo"},{"speciesCode":"belvir","comName":"Bell's Vireo"},{"speciesCode":"gryvir","comName":"Gray Vireo"},{"speciesCode":"hutvir","comName":"Hutton's Vireo"},{"speciesCode":"yetvir","comName":"Yellow-throated Vireo"},{"speciesCode":"casvir","comName":"Cassin's Vireo"},{"speciesCode":"buhvir","comName":"Blue-headed Vireo"},{"speciesCode":"plsvir","comName":"Plumbeous Vireo"},{"speciesCode":"phivir","comName":"Philadelphia Vireo"},{"speciesCode":"warvir","comName":"Warbling Vireo"},{"speciesCode":"reevir1","comName":"Red-eyed Vireo"},{"speciesCode":"yegvir","comName":"Yellow-green Vireo"},{"speciesCode":"bkwvir","comName":"Black-whiskered Vireo"},{"speciesCode":"yucvir","comName":"Yucatan Vireo"},{"speciesCode":"elepai","comName":"Hawaii Elepaio"},{"speciesCode":"elepai5","comName":"Kauai Elepaio"},{"speciesCode":"elepai4","comName":"Oahu Elepaio"},{"speciesCode":"rebshr1","comName":"Red-backed Shrike"},{"speciesCode":"brnshr","comName":"Brown Shrike"},{"speciesCode":"logshr","comName":"Loggerhead Shrike"},{"speciesCode":"norshr4","comName":"Northern Shrike"},{"speciesCode":"gryjay","comName":"Canada Jay"},{"speciesCode":"btmjay","comName":"Black-throated Magpie-Jay"},{"speciesCode":"brnjay","comName":"Brown Jay"},{"speciesCode":"grnjay","comName":"Green Jay"},{"speciesCode":"pinjay","comName":"Pinyon Jay"},{"speciesCode":"stejay","comName":"Steller's Jay"},{"speciesCode":"blujay","comName":"Blue Jay"},{"speciesCode":"flsjay","comName":"Florida Scrub-Jay"},{"speciesCode":"issjay","comName":"Island Scrub-Jay"},{"speciesCode":"cowscj1","comName":"California Scrub-Jay"},{"speciesCode":"wooscj2","comName":"Woodhouse's Scrub-Jay"},{"speciesCode":"mexjay4","comName":"Mexican Jay"},{"speciesCode":"bkbmag1","comName":"Black-billed Magpie"},{"speciesCode":"yebmag","comName":"Yellow-billed Magpie"},{"speciesCode":"clanut","comName":"Clark's Nutcracker"},{"speciesCode":"eurjac","comName":"Eurasian Jackdaw"},{"speciesCode":"houcro1","comName":"House Crow"},{"speciesCode":"amecro","comName":"American Crow"},{"speciesCode":"tamcro","comName":"Tamaulipas Crow"},{"speciesCode":"fiscro","comName":"Fish Crow"},{"speciesCode":"hawcro","comName":"Hawaiian Crow"},{"speciesCode":"chirav","comName":"Chihuahuan Raven"},{"speciesCode":"comrav","comName":"Common Raven"},{"speciesCode":"carchi","comName":"Carolina Chickadee"},{"speciesCode":"bkcchi","comName":"Black-capped Chickadee"},{"speciesCode":"mouchi","comName":"Mountain Chickadee"},{"speciesCode":"mexchi","comName":"Mexican Chickadee"},{"speciesCode":"chbchi","comName":"Chestnut-backed Chickadee"},{"speciesCode":"borchi2","comName":"Boreal Chickadee"},{"speciesCode":"gyhchi","comName":"Gray-headed Chickadee"},{"speciesCode":"britit","comName":"Bridled Titmouse"},{"speciesCode":"oaktit","comName":"Oak Titmouse"},{"speciesCode":"juntit1","comName":"Juniper Titmouse"},{"speciesCode":"tuftit","comName":"Tufted Titmouse"},{"speciesCode":"blctit4","comName":"Black-crested Titmouse"},{"speciesCode":"gretit1","comName":"Great Tit"},{"speciesCode":"verdin","comName":"Verdin"},{"speciesCode":"horlar","comName":"Horned Lark"},{"speciesCode":"skylar","comName":"Eurasian Skylark"},{"speciesCode":"thbwar1","comName":"Thick-billed Warbler"},{"speciesCode":"sedwar1","comName":"Sedge Warbler"},{"speciesCode":"blrwar1","comName":"Blyth's Reed Warbler"},{"speciesCode":"miller","comName":"Millerbird"},{"speciesCode":"pagwar1","comName":"Pallas's Grasshopper Warbler"},{"speciesCode":"migwar","comName":"Middendorff's Grasshopper Warbler"},{"speciesCode":"lanwar","comName":"Lanceolated Warbler"},{"speciesCode":"eurwar2","comName":"River Warbler"},{"speciesCode":"bawswa1","comName":"Blue-and-white Swallow"},{"speciesCode":"nrwswa","comName":"Northern Rough-winged Swallow"},{"speciesCode":"purmar","comName":"Purple Martin"},{"speciesCode":"cubmar","comName":"Cuban Martin"},{"speciesCode":"gybmar","comName":"Gray-breasted Martin"},{"speciesCode":"soumar","comName":"Southern Martin"},{"speciesCode":"brcmar1","comName":"Brown-chested Martin"},{"speciesCode":"treswa","comName":"Tree Swallow"},{"speciesCode":"manswa1","comName":"Mangrove Swallow"},{"speciesCode":"vigswa","comName":"Violet-green Swallow"},{"speciesCode":"bahswa","comName":"Bahama Swallow"},{"speciesCode":"banswa","comName":"Bank Swallow"},{"speciesCode":"barswa","comName":"Barn Swallow"},{"speciesCode":"cliswa","comName":"Cliff Swallow"},{"speciesCode":"cavswa","comName":"Cave Swallow"},{"speciesCode":"cohmar1","comName":"Common House-Martin"},{"speciesCode":"revbul","comName":"Red-vented Bulbul"},{"speciesCode":"rewbul","comName":"Red-whiskered Bulbul"},{"speciesCode":"woowar","comName":"Wood Warbler"},{"speciesCode":"yebwar3","comName":"Yellow-browed Warbler"},{"speciesCode":"palwar5","comName":"Pallas's Leaf Warbler"},{"speciesCode":"duswar","comName":"Dusky Warbler"},{"speciesCode":"wlwwar","comName":"Willow Warbler"},{"speciesCode":"comchi1","comName":"Common Chiffchaff"},{"speciesCode":"arcwar1","comName":"Arctic Warbler"},{"speciesCode":"arcwar2","comName":"Kamchatka Leaf Warbler"},{"speciesCode":"jabwar","comName":"Japanese Bush Warbler"},{"speciesCode":"bushti","comName":"Bushtit"},{"speciesCode":"leswhi4","comName":"Lesser Whitethroat"},{"speciesCode":"wrenti","comName":"Wrentit"},{"speciesCode":"swiwhe1","comName":"Swinhoe's White-eye"},{"speciesCode":"warwhe1","comName":"Warbling White-eye"},{"speciesCode":"indwhe1","comName":"Indian White-eye"},{"speciesCode":"reblei","comName":"Red-billed Leiothrix"},{"speciesCode":"melthr","comName":"Chinese Hwamei"},{"speciesCode":"gnlthr","comName":"Greater Necklaced Laughingthrush"},{"speciesCode":"ruckin","comName":"Ruby-crowned Kinglet"},{"speciesCode":"gockin","comName":"Golden-crowned Kinglet"},{"speciesCode":"rebnut","comName":"Red-breasted Nuthatch"},{"speciesCode":"whbnut","comName":"White-breasted Nuthatch"},{"speciesCode":"pygnut","comName":"Pygmy Nuthatch"},{"speciesCode":"bnhnut","comName":"Brown-headed Nuthatch"},{"speciesCode":"brncre","comName":"Brown Creeper"},{"speciesCode":"buggna","comName":"Blue-gray Gnatcatcher"},{"speciesCode":"bktgna","comName":"Black-tailed Gnatcatcher"},{"speciesCode":"calgna","comName":"California Gnatcatcher"},{"speciesCode":"bkcgna","comName":"Black-capped Gnatcatcher"},{"speciesCode":"rocwre","comName":"Rock Wren"},{"speciesCode":"canwre","comName":"Canyon Wren"},{"speciesCode":"houwre","comName":"House Wren"},{"speciesCode":"pacwre1","comName":"Pacific Wren"},{"speciesCode":"winwre3","comName":"Winter Wren"},{"speciesCode":"sedwre1","comName":"Sedge Wren"},{"speciesCode":"marwre","comName":"Marsh Wren"},{"speciesCode":"carwre","comName":"Carolina Wren"},{"speciesCode":"bewwre","comName":"Bewick's Wren"},{"speciesCode":"cacwre","comName":"Cactus Wren"},{"speciesCode":"sinwre1","comName":"Sinaloa Wren"},{"speciesCode":"amedip","comName":"American Dipper"},{"speciesCode":"hilmyn","comName":"Common Hill Myna"},{"speciesCode":"eursta","comName":"European Starling"},{"speciesCode":"commyn","comName":"Common Myna"},{"speciesCode":"blumoc","comName":"Blue Mockingbird"},{"speciesCode":"grycat","comName":"Gray Catbird"},{"speciesCode":"cubthr","comName":"Curve-billed Thrasher"},{"speciesCode":"brnthr","comName":"Brown Thrasher"},{"speciesCode":"lobthr","comName":"Long-billed Thrasher"},{"speciesCode":"benthr","comName":"Bendire's Thrasher"},{"speciesCode":"calthr","comName":"California Thrasher"},{"speciesCode":"lecthr","comName":"LeConte's Thrasher"},{"speciesCode":"crithr","comName":"Crissal Thrasher"},{"speciesCode":"sagthr","comName":"Sage Thrasher"},{"speciesCode":"bahmoc","comName":"Bahama Mockingbird"},{"speciesCode":"tromoc","comName":"Tropical Mockingbird"},{"speciesCode":"normoc","comName":"Northern Mockingbird"},{"speciesCode":"easblu","comName":"Eastern Bluebird"},{"speciesCode":"wesblu","comName":"Western Bluebird"},{"speciesCode":"moublu","comName":"Mountain Bluebird"},{"speciesCode":"towsol","comName":"Townsend's Solitaire"},{"speciesCode":"brbsol1","comName":"Brown-backed Solitaire"},{"speciesCode":"kamao","comName":"Kamao"},{"speciesCode":"olomao","comName":"Olomao"},{"speciesCode":"omao","comName":"Omao"},{"speciesCode":"puaioh","comName":"Puaiohi"},{"speciesCode":"varthr","comName":"Varied Thrush"},{"speciesCode":"obnthr1","comName":"Orange-billed Nightingale-Thrush"},{"speciesCode":"bhnthr1","comName":"Black-headed Nightingale-Thrush"},{"speciesCode":"veery","comName":"Veery"},{"speciesCode":"gycthr","comName":"Gray-cheeked Thrush"},{"speciesCode":"bicthr","comName":"Bicknell's Thrush"},{"speciesCode":"swathr","comName":"Swainson's Thrush"},{"speciesCode":"herthr","comName":"Hermit Thrush"},{"speciesCode":"woothr","comName":"Wood Thrush"},{"speciesCode":"aztthr","comName":"Aztec Thrush"},{"speciesCode":"sonthr1","comName":"Song Thrush"},{"speciesCode":"redwin","comName":"Redwing"},{"speciesCode":"whtrob1","comName":"White-throated Thrush"},{"speciesCode":"clcrob","comName":"Clay-colored Thrush"},{"speciesCode":"amerob","comName":"American Robin"},{"speciesCode":"rubrob","comName":"Rufous-backed Robin"},{"speciesCode":"relthr1","comName":"Red-legged Thrush"},{"speciesCode":"eyethr","comName":"Eyebrowed Thrush"},{"speciesCode":"fieldf","comName":"Fieldfare"},{"speciesCode":"dusthr2","comName":"Dusky Thrush"},{"speciesCode":"dusthr1","comName":"Naumann's Thrush"},{"speciesCode":"gysfly1","comName":"Gray-streaked Flycatcher"},{"speciesCode":"dasfly","comName":"Dark-sided Flycatcher"},{"speciesCode":"asbfly","comName":"Asian Brown Flycatcher"},{"speciesCode":"spofly1","comName":"Spotted Flycatcher"},{"speciesCode":"whrsha","comName":"White-rumped Shama"},{"speciesCode":"eurrob1","comName":"European Robin"},{"speciesCode":"rutrob1","comName":"Rufous-tailed Robin"},{"speciesCode":"sibrob","comName":"Siberian Blue Robin"},{"speciesCode":"blueth","comName":"Bluethroat"},{"speciesCode":"sibrub","comName":"Siberian Rubythroat"},{"speciesCode":"refblu","comName":"Red-flanked Bluetail"},{"speciesCode":"narfly2","comName":"Narcissus Flycatcher"},{"speciesCode":"mugfly","comName":"Mugimaki Flycatcher"},{"speciesCode":"taifly1","comName":"Taiga Flycatcher"},{"speciesCode":"rebfly","comName":"Red-breasted Flycatcher"},{"speciesCode":"comred2","comName":"Common Redstart"},{"speciesCode":"rtrthr1","comName":"Rufous-tailed Rock-Thrush"},{"speciesCode":"sibsto1","comName":"Siberian Stonechat"},{"speciesCode":"norwhe","comName":"Northern Wheatear"},{"speciesCode":"piewhe1","comName":"Pied Wheatear"},{"speciesCode":"bohwax","comName":"Bohemian Waxwing"},{"speciesCode":"cedwax","comName":"Cedar Waxwing"},{"speciesCode":"kauoo","comName":"Kauai Oo"},{"speciesCode":"grsfly1","comName":"Gray Silky-flycatcher"},{"speciesCode":"phaino","comName":"Phainopepla"},{"speciesCode":"oliwar","comName":"Olive Warbler"},{"speciesCode":"orabis1","comName":"Northern Red Bishop"},{"speciesCode":"zebfin2","comName":"Zebra Finch"},{"speciesCode":"broman1","comName":"Bronze Mannikin"},{"speciesCode":"afrsil1","comName":"African Silverbill"},{"speciesCode":"javspa","comName":"Java Sparrow"},{"speciesCode":"nutman","comName":"Scaly-breasted Munia"},{"speciesCode":"blfmun1","comName":"Black-faced Munia"},{"speciesCode":"trimun","comName":"Tricolored Munia"},{"speciesCode":"chemun","comName":"Chestnut Munia"},{"speciesCode":"lavwax","comName":"Lavender Waxbill"},{"speciesCode":"orcwax","comName":"Orange-cheeked Waxbill"},{"speciesCode":"comwax","comName":"Common Waxbill"},{"speciesCode":"bkrwax","comName":"Black-rumped Waxbill"},{"speciesCode":"redava","comName":"Red Avadavat"},{"speciesCode":"reccor","comName":"Red-cheeked Cordonbleu"},{"speciesCode":"pitwhy","comName":"Pin-tailed Whydah"},{"speciesCode":"sibacc","comName":"Siberian Accentor"},{"speciesCode":"houspa","comName":"House Sparrow"},{"speciesCode":"eutspa","comName":"Eurasian Tree Sparrow"},{"speciesCode":"grywag","comName":"Gray Wagtail"},{"speciesCode":"eaywag1","comName":"Western Yellow Wagtail"},{"speciesCode":"eaywag","comName":"Eastern Yellow Wagtail"},{"speciesCode":"citwag","comName":"Citrine Wagtail"},{"speciesCode":"whiwag","comName":"White Wagtail"},{"speciesCode":"trepip","comName":"Tree Pipit"},{"speciesCode":"olbpip","comName":"Olive-backed Pipit"},{"speciesCode":"pecpip","comName":"Pechora Pipit"},{"speciesCode":"retpip","comName":"Red-throated Pipit"},{"speciesCode":"amepip","comName":"American Pipit"},{"speciesCode":"sprpip","comName":"Sprague's Pipit"},{"speciesCode":"comcha","comName":"Common Chaffinch"},{"speciesCode":"brambl","comName":"Brambling"},{"speciesCode":"evegro","comName":"Evening Grosbeak"},{"speciesCode":"hawfin","comName":"Hawfinch"},{"speciesCode":"poouli","comName":"Poo-uli"},{"speciesCode":"akikik","comName":"Akikiki"},{"speciesCode":"mauala","comName":"Maui Alauahio"},{"speciesCode":"palila","comName":"Palila"},{"speciesCode":"layfin","comName":"Laysan Finch"},{"speciesCode":"nihfin","comName":"Nihoa Finch"},{"speciesCode":"crehon","comName":"Akohekohe"},{"speciesCode":"apapan","comName":"Apapane"},{"speciesCode":"iiwi","comName":"Iiwi"},{"speciesCode":"ou","comName":"Ou"},{"speciesCode":"maupar","comName":"Maui Parrotbill"},{"speciesCode":"nukupu2","comName":"Kauai Nukupuu"},{"speciesCode":"akiapo","comName":"Akiapolaau"},{"speciesCode":"aniani","comName":"Anianiau"},{"speciesCode":"hawama","comName":"Hawaii Amakihi"},{"speciesCode":"oahama","comName":"Oahu Amakihi"},{"speciesCode":"kauama","comName":"Kauai Amakihi"},{"speciesCode":"hawcre","comName":"Hawaii Creeper"},{"speciesCode":"akekee","comName":"Akekee"},{"speciesCode":"akepa1","comName":"Hawaii Akepa"},{"speciesCode":"akepa3","comName":"Maui Akepa"},{"speciesCode":"comros","comName":"Common Rosefinch"},{"speciesCode":"palros2","comName":"Pallas's Rosefinch"},{"speciesCode":"pingro","comName":"Pine Grosbeak"},{"speciesCode":"eurbul","comName":"Eurasian Bullfinch"},{"speciesCode":"asrfin1","comName":"Asian Rosy-Finch"},{"speciesCode":"gcrfin","comName":"Gray-crowned Rosy-Finch"},{"speciesCode":"bkrfin","comName":"Black Rosy-Finch"},{"speciesCode":"bcrfin","comName":"Brown-capped Rosy-Finch"},{"speciesCode":"houfin","comName":"House Finch"},{"speciesCode":"purfin","comName":"Purple Finch"},{"speciesCode":"casfin","comName":"Cassin's Finch"},{"speciesCode":"eurgre1","comName":"European Greenfinch"},{"speciesCode":"origre","comName":"Oriental Greenfinch"},{"speciesCode":"yefcan","comName":"Yellow-fronted Canary"},{"speciesCode":"comred","comName":"Common Redpoll"},{"speciesCode":"hoared","comName":"Hoary Redpoll"},{"speciesCode":"redcro","comName":"Red Crossbill"},{"speciesCode":"redcro9","comName":"Cassia Crossbill"},{"speciesCode":"whwcro","comName":"White-winged Crossbill"},{"speciesCode":"eurgol","comName":"European Goldfinch"},{"speciesCode":"eursis","comName":"Eurasian Siskin"},{"speciesCode":"pinsis","comName":"Pine Siskin"},{"speciesCode":"lesgol","comName":"Lesser Goldfinch"},{"speciesCode":"lawgol","comName":"Lawrence's Goldfinch"},{"speciesCode":"amegfi","comName":"American Goldfinch"},{"speciesCode":"laplon","comName":"Lapland Longspur"},{"speciesCode":"chclon","comName":"Chestnut-collared Longspur"},{"speciesCode":"smilon","comName":"Smith's Longspur"},{"speciesCode":"mcclon","comName":"Thick-billed Longspur"},{"speciesCode":"snobun","comName":"Snow Bunting"},{"speciesCode":"mckbun","comName":"McKay's Bunting"},{"speciesCode":"pinbun","comName":"Pine Bunting"},{"speciesCode":"yetbun1","comName":"Yellow-throated Bunting"},{"speciesCode":"palbun","comName":"Pallas's Bunting"},{"speciesCode":"reebun","comName":"Reed Bunting"},{"speciesCode":"yebbun","comName":"Yellow-breasted Bunting"},{"speciesCode":"litbun","comName":"Little Bunting"},{"speciesCode":"rusbun","comName":"Rustic Bunting"},{"speciesCode":"yebbun1","comName":"Yellow-browed Bunting"},{"speciesCode":"grybun","comName":"Gray Bunting"},{"speciesCode":"ruwspa","comName":"Rufous-winged Sparrow"},{"speciesCode":"botspa","comName":"Botteri's Sparrow"},{"speciesCode":"casspa","comName":"Cassin's Sparrow"},{"speciesCode":"bacspa","comName":"Bachman's Sparrow"},{"speciesCode":"graspa","comName":"Grasshopper Sparrow"},{"speciesCode":"olispa","comName":"Olive Sparrow"},{"speciesCode":"fisspa","comName":"Five-striped Sparrow"},{"speciesCode":"chispa","comName":"Chipping Sparrow"},{"speciesCode":"clcspa","comName":"Clay-colored Sparrow"},{"speciesCode":"bkcspa","comName":"Black-chinned Sparrow"},{"speciesCode":"fiespa","comName":"Field Sparrow"},{"speciesCode":"brespa","comName":"Brewer's Sparrow"},{"speciesCode":"worspa","comName":"Worthen's Sparrow"},{"speciesCode":"bktspa","comName":"Black-throated Sparrow"},{"speciesCode":"larspa","comName":"Lark Sparrow"},{"speciesCode":"larbun","comName":"Lark Bunting"},{"speciesCode":"amtspa","comName":"American Tree Sparrow"},{"speciesCode":"foxspa","comName":"Fox Sparrow"},{"speciesCode":"daejun","comName":"Dark-eyed Junco"},{"speciesCode":"yeejun","comName":"Yellow-eyed Junco"},{"speciesCode":"whcspa","comName":"White-crowned Sparrow"},{"speciesCode":"gocspa","comName":"Golden-crowned Sparrow"},{"speciesCode":"harspa","comName":"Harris's Sparrow"},{"speciesCode":"whtspa","comName":"White-throated Sparrow"},{"speciesCode":"sagspa1","comName":"Sagebrush Sparrow"},{"speciesCode":"belspa2","comName":"Bell's Sparrow"},{"speciesCode":"strspa1","comName":"Striped Sparrow"},{"speciesCode":"vesspa","comName":"Vesper Sparrow"},{"speciesCode":"lecspa","comName":"LeConte's Sparrow"},{"speciesCode":"seaspa","comName":"Seaside Sparrow"},{"speciesCode":"nstspa","comName":"Nelson's Sparrow"},{"speciesCode":"sstspa","comName":"Saltmarsh Sparrow"},{"speciesCode":"savspa","comName":"Savannah Sparrow"},{"speciesCode":"baispa","comName":"Baird's Sparrow"},{"speciesCode":"henspa","comName":"Henslow's Sparrow"},{"speciesCode":"sonspa","comName":"Song Sparrow"},{"speciesCode":"linspa","comName":"Lincoln's Sparrow"},{"speciesCode":"swaspa","comName":"Swamp Sparrow"},{"speciesCode":"cantow","comName":"Canyon Towhee"},{"speciesCode":"abetow","comName":"Abert's Towhee"},{"speciesCode":"caltow","comName":"California Towhee"},{"speciesCode":"rucspa","comName":"Rufous-crowned Sparrow"},{"speciesCode":"gnttow","comName":"Green-tailed Towhee"},{"speciesCode":"spotow","comName":"Spotted Towhee"},{"speciesCode":"eastow","comName":"Eastern Towhee"},{"speciesCode":"wesspi","comName":"Western Spindalis"},{"speciesCode":"yebcha","comName":"Yellow-breasted Chat"},{"speciesCode":"yehbla","comName":"Yellow-headed Blackbird"},{"speciesCode":"boboli","comName":"Bobolink"},{"speciesCode":"wesmea","comName":"Western Meadowlark"},{"speciesCode":"easmea","comName":"Eastern Meadowlark"},{"speciesCode":"bkvori","comName":"Black-vented Oriole"},{"speciesCode":"orcori","comName":"Orchard Oriole"},{"speciesCode":"hooori","comName":"Hooded Oriole"},{"speciesCode":"stbori","comName":"Streak-backed Oriole"},{"speciesCode":"bulori","comName":"Bullock's Oriole"},{"speciesCode":"spbori","comName":"Spot-breasted Oriole"},{"speciesCode":"altori","comName":"Altamira Oriole"},{"speciesCode":"audori","comName":"Audubon's Oriole"},{"speciesCode":"balori","comName":"Baltimore Oriole"},{"speciesCode":"blbori1","comName":"Black-backed Oriole"},{"speciesCode":"scoori","comName":"Scott's Oriole"},{"speciesCode":"rewbla","comName":"Red-winged Blackbird"},{"speciesCode":"tribla","comName":"Tricolored Blackbird"},{"speciesCode":"tasbla","comName":"Tawny-shouldered Blackbird"},{"speciesCode":"shicow","comName":"Shiny Cowbird"},{"speciesCode":"brocow","comName":"Bronzed Cowbird"},{"speciesCode":"bnhcow","comName":"Brown-headed Cowbird"},{"speciesCode":"rusbla","comName":"Rusty Blackbird"},{"speciesCode":"brebla","comName":"Brewer's Blackbird"},{"speciesCode":"comgra","comName":"Common Grackle"},{"speciesCode":"botgra","comName":"Boat-tailed Grackle"},{"speciesCode":"grtgra","comName":"Great-tailed Grackle"},{"speciesCode":"ovenbi1","comName":"Ovenbird"},{"speciesCode":"woewar1","comName":"Worm-eating Warbler"},{"speciesCode":"louwat","comName":"Louisiana Waterthrush"},{"speciesCode":"norwat","comName":"Northern Waterthrush"},{"speciesCode":"bacwar","comName":"Bachman's Warbler"},{"speciesCode":"gowwar","comName":"Golden-winged Warbler"},{"speciesCode":"buwwar","comName":"Blue-winged Warbler"},{"speciesCode":"bawwar","comName":"Black-and-white Warbler"},{"speciesCode":"prowar","comName":"Prothonotary Warbler"},{"speciesCode":"swawar","comName":"Swainson's Warbler"},{"speciesCode":"crcwar","comName":"Crescent-chested Warbler"},{"speciesCode":"tenwar","comName":"Tennessee Warbler"},{"speciesCode":"orcwar","comName":"Orange-crowned Warbler"},{"speciesCode":"colwar","comName":"Colima Warbler"},{"speciesCode":"lucwar","comName":"Lucy's Warbler"},{"speciesCode":"naswar","comName":"Nashville Warbler"},{"speciesCode":"virwar","comName":"Virginia's Warbler"},{"speciesCode":"conwar","comName":"Connecticut Warbler"},{"speciesCode":"gycyel","comName":"Gray-crowned Yellowthroat"},{"speciesCode":"macwar","comName":"MacGillivray's Warbler"},{"speciesCode":"mouwar","comName":"Mourning Warbler"},{"speciesCode":"kenwar","comName":"Kentucky Warbler"},{"speciesCode":"comyel","comName":"Common Yellowthroat"},{"speciesCode":"hoowar","comName":"Hooded Warbler"},{"speciesCode":"amered","comName":"American Redstart"},{"speciesCode":"kirwar","comName":"Kirtland's Warbler"},{"speciesCode":"camwar","comName":"Cape May Warbler"},{"speciesCode":"cerwar","comName":"Cerulean Warbler"},{"speciesCode":"norpar","comName":"Northern Parula"},{"speciesCode":"tropar","comName":"Tropical Parula"},{"speciesCode":"magwar","comName":"Magnolia Warbler"},{"speciesCode":"babwar","comName":"Bay-breasted Warbler"},{"speciesCode":"bkbwar","comName":"Blackburnian Warbler"},{"speciesCode":"yelwar","comName":"Yellow Warbler"},{"speciesCode":"chswar","comName":"Chestnut-sided Warbler"},{"speciesCode":"bkpwar","comName":"Blackpoll Warbler"},{"speciesCode":"btbwar","comName":"Black-throated Blue Warbler"},{"speciesCode":"palwar","comName":"Palm Warbler"},{"speciesCode":"pinwar","comName":"Pine Warbler"},{"speciesCode":"yerwar","comName":"Yellow-rumped Warbler"},{"speciesCode":"yetwar","comName":"Yellow-throated Warbler"},{"speciesCode":"prawar","comName":"Prairie Warbler"},{"speciesCode":"grawar","comName":"Grace's Warbler"},{"speciesCode":"btywar","comName":"Black-throated Gray Warbler"},{"speciesCode":"towwar","comName":"Townsend's Warbler"},{"speciesCode":"herwar","comName":"Hermit Warbler"},{"speciesCode":"gchwar","comName":"Golden-cheeked Warbler"},{"speciesCode":"btnwar","comName":"Black-throated Green Warbler"},{"speciesCode":"fatwar","comName":"Fan-tailed Warbler"},{"speciesCode":"rucwar","comName":"Rufous-capped Warbler"},{"speciesCode":"gcrwar","comName":"Golden-crowned Warbler"},{"speciesCode":"canwar","comName":"Canada Warbler"},{"speciesCode":"wlswar","comName":"Wilson's Warbler"},{"speciesCode":"refwar","comName":"Red-faced Warbler"},{"speciesCode":"paired","comName":"Painted Redstart"},{"speciesCode":"sltred","comName":"Slate-throated Redstart"},{"speciesCode":"heptan","comName":"Hepatic Tanager"},{"speciesCode":"sumtan","comName":"Summer Tanager"},{"speciesCode":"scatan","comName":"Scarlet Tanager"},{"speciesCode":"westan","comName":"Western Tanager"},{"speciesCode":"flctan","comName":"Flame-colored Tanager"},{"speciesCode":"crcgro","comName":"Crimson-collared Grosbeak"},{"speciesCode":"norcar","comName":"Northern Cardinal"},{"speciesCode":"pyrrhu","comName":"Pyrrhuloxia"},{"speciesCode":"yelgro","comName":"Yellow Grosbeak"},{"speciesCode":"robgro","comName":"Rose-breasted Grosbeak"},{"speciesCode":"bkhgro","comName":"Black-headed Grosbeak"},{"speciesCode":"blubun","comName":"Blue Bunting"},{"speciesCode":"blugrb1","comName":"Blue Grosbeak"},{"speciesCode":"lazbun","comName":"Lazuli Bunting"},{"speciesCode":"indbun","comName":"Indigo Bunting"},{"speciesCode":"varbun","comName":"Varied Bunting"},{"speciesCode":"paibun","comName":"Painted Bunting"},{"speciesCode":"dickci","comName":"Dickcissel"},{"speciesCode":"reccar","comName":"Red-crested Cardinal"},{"speciesCode":"yebcar","comName":"Yellow-billed Cardinal"},{"speciesCode":"relhon1","comName":"Red-legged Honeycreeper"},{"speciesCode":"saffin","comName":"Saffron Finch"},{"speciesCode":"whcsee1","comName":"Morelet's Seedeater"},{"speciesCode":"whcsee2","comName":"Cinnamon-rumped Seedeater"},{"speciesCode":"banana","comName":"Bananaquit"},{"speciesCode":"yefgra1","comName":"Yellow-faced Grassquit"},{"speciesCode":"cubgra","comName":"Cuban Grassquit"},{"speciesCode":"bkfgra","comName":"Black-faced Grassquit"}]